{
  "$schema": "http://bigcontent.io/cms/schema/v1/schema#",
  "id": "https://presalesadisws.s3.eu-west-1.amazonaws.com/dynamic-content/accelerators/ultapoc/contentSchemas/text.json",
  "title": "Text",
  "description": "Text accelerator",
  "allOf": [
    {
      "$ref": "http://bigcontent.io/cms/schema/v1/core#/definitions/content"
    }
  ],
  "type": "object",
  "properties": {
    "text": {
      "type": "string",
      "format": "markdown",
      "title": "Text",
      "minLength": 0,
      "maxLength": 6000
    }
  },
  "propertyOrder": [
    "text"
  ]
}